svg_to_pdf-0.1.2.dist-info/METADATA
svg_to_pdf-0.1.2.dist-info/WHEEL
svg_to_pdf/__init__.py
svg_to_pdf/ffi.py
svg_to_pdf/svg_to_pdf.so
svg_to_pdf-0.1.2.dist-info/RECORD
